{
  "main": {
    "id": "f614b18e3194bcbb",
    "type": "split",
    "children": [
      {
        "id": "e7a806e722f39f6f",
        "type": "tabs",
        "children": [
          {
            "id": "e547d7cca721013f",
            "type": "leaf",
            "state": {
              "type": "markdown",
              "state": {
                "file": "Generators/Interface.md",
                "mode": "preview",
                "source": true
              }
            }
          }
        ]
      }
    ],
    "direction": "vertical"
  },
  "left": {
    "id": "07fd42b6f545db37",
    "type": "mobile-drawer",
    "children": [
      {
        "id": "58b205c0d5936af6",
        "type": "leaf",
        "state": {
          "type": "file-explorer",
          "state": {
            "sortOrder": "alphabetical"
          }
        }
      },
      {
        "id": "ff44d147874654f1",
        "type": "leaf",
        "state": {
          "type": "search",
          "state": {
            "query": "",
            "matchingCase": true,
            "explainSearch": false,
            "collapseAll": false,
            "extraContext": false,
            "sortOrder": "alphabetical"
          }
        }
      },
      {
        "id": "134cf037425764bf",
        "type": "leaf",
        "state": {
          "type": "tag",
          "state": {
            "sortOrder": "frequency",
            "useHierarchy": true
          }
        }
      },
      {
        "id": "0bb2d2b77e1c4a1e",
        "type": "leaf",
        "state": {
          "type": "starred",
          "state": {}
        }
      }
    ],
    "currentTab": 0
  },
  "right": {
    "id": "a12bf307afce4cab",
    "type": "mobile-drawer",
    "children": [
      {
        "id": "39d8ac061361f927",
        "type": "leaf",
        "state": {
          "type": "backlink",
          "state": {
            "file": "Generators/Interface.md",
            "collapseAll": false,
            "extraContext": false,
            "sortOrder": "alphabetical",
            "showSearch": false,
            "searchQuery": "",
            "backlinkCollapsed": false,
            "unlinkedCollapsed": true
          }
        }
      },
      {
        "id": "913ab2b5c5b63f28",
        "type": "leaf",
        "state": {
          "type": "outgoing-link",
          "state": {
            "file": "Generators/Interface.md",
            "linksCollapsed": false,
            "unlinkedCollapsed": true
          }
        }
      },
      {
        "id": "3158d4ac8a64154e",
        "type": "leaf",
        "state": {
          "type": "outline",
          "state": {
            "file": "Generators/Interface.md"
          }
        }
      },
      {
        "id": "38da039c4cb2a155",
        "type": "leaf",
        "state": {
          "type": "calendar",
          "state": {}
        }
      },
      {
        "id": "c05f109102883e7d",
        "type": "leaf",
        "state": {
          "type": "advanced-tables-toolbar",
          "state": {}
        }
      },
      {
        "id": "865d1b9aee4a1970",
        "type": "leaf",
        "state": {
          "type": "online.larslockefeer.obsidian-plugin-todo",
          "state": {}
        }
      }
    ],
    "currentTab": 4
  },
  "left-ribbon": {
    "hiddenItems": {
      "table-editor-obsidian:Advanced Tables Toolbar": false,
      "switcher:Open quick switcher": false,
      "graph:Open graph view": false,
      "canvas:Create new canvas": false,
      "templates:Insert template": false,
      "command-palette:Open command palette": false,
      "obsidian-excalidraw-plugin:Create new drawing": false,
      "homepage:Open homepage": false
    }
  },
  "active": "e547d7cca721013f",
  "lastOpenFiles": [
    "Generators/Interface.md",
    "Home.md",
    "Generators",
    "Research/Scrap..md",
    "Classes/Spring 2023/Algebra/Exam 2 Question 4.md",
    "Research/Untitled.md",
    "Read Later.md",
    "Research/Tangle Translation/Tangle.md",
    "Research/Tangle Translation/Untitled 1.md",
    "Research/Tangle Translation/Untitled.md",
    "Research/Tangle Translation/media/c485348589c7af24c84418a4dfe7a278.png",
    "Research/Tangle Translation/media/f30785b1885f9aaadeda78dcce241b9f.png",
    "Research/Tangle Translation/media/4de31977f71bc6ef850c2c0e4e0cc20b.png",
    "Research/Tangle Translation/media/eee0094e808c4e863445b76dcbef580a.png",
    "Research/Tangle Translation/media/21c43e9bc65886f463ad85126aae5e32.png",
    "Research/Tangle Translation/media/952717e430fa090b60fe41a128bf19f2.png",
    "kanban/Week 2.md",
    "kanban/Board.md",
    "Classes/Spring 2023/Numerical Analysis/Hw 5.md",
    "Research/Rational Tangle Upper Bound.md",
    "Classes/Spring 2023/Algebra/Exam.md",
    "Research/Tangle Translation/media/Drawing2023-04-16 00.36.49.excalidraw.md",
    "Research/Tangle Translation/media/Drawing2023-04-16 00.37.26.excalidraw.md",
    "Research/Summer list.md",
    "Research/Braids.md",
    "Research/DT Notation.md",
    "Untitled 1.canvas",
    "Research/media/ade1fa71f1703f03c1deb03a637bf53d.png",
    "Research/media",
    "Untitled.canvas",
    "Template.excalidraw.md",
    "What Is/MVSG.md",
    "Classes/Spring 2023/Algebra/Defintions.md",
    "Classes/Spring 2023/Algebra/media/450d168198d5f36db25c5a4396507541.png",
    "Classes/Spring 2023/Algebra/media/c6b146f89c0a94813cd84ae68de5a592.png",
    "kanban/Week 14.md",
    "Classes/Spring 2023/Numerical Analysis/2.1.md",
    "What Is/DT/DT Code.md",
    "What Is/DT/6_2 13.svg",
    "Classes/Spring 2023/Numerical Analysis/Qual.md",
    "What Is/DT",
    "What Is",
    "Research/Connolly",
    "get_todo_obsidian.py",
    "config.json",
    "update_todo.bat"
  ]
}